discord/ext/timers/__init__.py
discord/ext/timers/timers.py
discord/ext/timers/utils.py
discord_timers-0.1.0.dist-info/LICENSE
discord_timers-0.1.0.dist-info/METADATA
discord_timers-0.1.0.dist-info/WHEEL
discord_timers-0.1.0.dist-info/top_level.txt
discord_timers-0.1.0.dist-info/RECORD
