Metadata-Version: 2.1
Name: discord-timers
Version: 0.1.0
Summary: Timers for bots made with discord.py
Home-page: https://github.com/PendragonLore/discord-timers
Author: Lorenzo
License: MIT
Project-URL: Code, https://github.com/PendragonLore/discord-timers
Project-URL: Issue tracker, https://github.com/PendragonLore/discord-timers/issues
Keywords: asyncio,discord,timers
Platform: any
Classifier: License :: OSI Approved :: MIT License
Classifier: Framework :: AsyncIO
Classifier: Programming Language :: Python :: 3 :: Only
Classifier: Programming Language :: Python :: 3.5
Classifier: Programming Language :: Python :: 3.6
Classifier: Programming Language :: Python :: 3.7
Classifier: Programming Language :: Python :: Implementation :: CPython
Classifier: Development Status :: 3 - Alpha
Classifier: Natural Language :: English
Classifier: Intended Audience :: Developers
Classifier: Operating System :: OS Independent
Classifier: Topic :: Internet
Classifier: Topic :: Utilities
Classifier: Topic :: Software Development :: Libraries
Requires-Python: >=3.5.3
